node_status_lib/__init__.py
node_status_lib/db.py
node_status_lib/enums.py
node_status_lib/manager.py
node_status_lib-0.1.17.dist-info/METADATA
node_status_lib-0.1.17.dist-info/WHEEL
node_status_lib-0.1.17.dist-info/top_level.txt
node_status_lib-0.1.17.dist-info/RECORD
