Metadata-Version: 2.4
Name: node-status-lib
Version: 0.1.17
Summary: A lightweight library for node and internal flow-level status tracking using PostgreSQL.
Author-email: Angelo Antu <angelo.antu@kireap.com>
License-Expression: MIT
Keywords: node,status
Requires-Python: >=3.10
Requires-Dist: psycopg2
Provides-Extra: dev
Requires-Dist: pytest; extra == "dev"
Requires-Dist: black; extra == "dev"
Requires-Dist: flake8; extra == "dev"
